sgfcmed_test-0.0.1.dist-info/licenses/LICENSE
test/__init__.py
test/test_sgfcmed.py
sgfcmed_test-0.0.1.dist-info/METADATA
sgfcmed_test-0.0.1.dist-info/WHEEL
sgfcmed_test-0.0.1.dist-info/top_level.txt
sgfcmed_test-0.0.1.dist-info/RECORD
