Metadata-Version: 2.4
Name: sgFCMed_test
Version: 0.0.1
Summary: Simply Lovely
Author: Nawawan Thaichim
Author-email: richwoon09@email.com
License: MIT
Requires-Python: >=3.7
License-File: LICENSE
Requires-Dist: pytest
Dynamic: author
Dynamic: author-email
Dynamic: description
Dynamic: description-content-type
Dynamic: license
Dynamic: license-file
Dynamic: requires-dist
Dynamic: requires-python
Dynamic: summary
